features.py
igpd_l.py
igpd_linux-0.1.6.dist-info/METADATA
igpd_linux-0.1.6.dist-info/WHEEL
igpd_linux-0.1.6.dist-info/top_level.txt
igpd_linux-0.1.6.dist-info/RECORD
