Metadata-Version: 2.1
Name: igpd-linux
Version: 0.1.6
Summary: Download almost everything from instagram, from public accounts and from your followers
Home-page: https://github.com/ahn1305/igpd-linux
Author: Ashwin.B
Author-email: ahnashwin1305@gmail.com
License: MIT
Platform: UNKNOWN
Classifier: Programming Language :: Python :: 3.6
Classifier: Programming Language :: Python :: 3.7
Classifier: Programming Language :: Python :: 3.8
Classifier: License :: OSI Approved :: MIT License
Classifier: Operating System :: POSIX :: Linux
Requires-Dist: instaloader (==4.5.5)
Requires-Dist: printtools (==1.2)
